rtl/mac.v
module mac_unit#(
    parameter WIDTH = 8, //8-bit integer
    parameter N = 2, // Size of matrix being multiplied
    parameter SUM_WIDTH = (WIDTH*2) + $clog2(N) + 1 // +1 guard bit
)(
    input clk,
    input rst,
    input [WIDTH-1:0] weight,
    input [WIDTH-1:0] act_in,
    input [SUM_WIDTH-1:0] sum_in,
    output reg [WIDTH-1:0] act_out, //goes up
    output reg [SUM_WIDTH-1:0] sum_out //goes right
);

    always @(posedge clk) begin
        if (rst) begin
            act_out <= 0;
            sum_out <= 0;
        end else begin
            act_out <= act_in;
            sum_out <= sum_in + (weight*act_in);
        end
    end

endmodule

rtl/systolic_2x2.v
module systolic_2x2 #(
    parameter WIDTH = 8,
    parameter N = 2,
    parameter SUM_WIDTH = (WIDTH*2) + $clog2(N) + 1   // same formula
)(
    input  clk, rst,
    input  [WIDTH-1:0] weights [0:1][0:1],
    input  [WIDTH-1:0] act_in_cols[0:1],
    output [SUM_WIDTH-1:0] sum_out_row_top, sum_out_row_bot
);

    // internal wires
    wire [WIDTH-1:0]     act_BL_to_TL, act_BR_to_TR;
    wire [SUM_WIDTH-1:0] sum_TL_to_TR, sum_BL_to_BR;
    wire [WIDTH-1:0]     act_top_out_L, act_top_out_R;  // unused, exits top

    // AUTOMATE LATER
    //(0,0)
    mac_unit mac_TL (
        .clk(clk), .rst(rst),
        .weight(weights[0][0]),
        .act_in(act_BL_to_TL),            // gets activation from below
        .sum_in({SUM_WIDTH{1'b0}}),       // leftmost: no sum coming in
        .act_out(act_top_out_L),          // top activation unused
        .sum_out(sum_TL_to_TR)            // sends sum right
    );
    //(1,0)
    mac_unit mac_BL (
        .clk(clk), .rst(rst),
        .weight(weights[1][0]),
        .act_in(act_in_cols[0]),             // activation vector
        .sum_in({SUM_WIDTH{1'b0}}),          // leftmost: no sum in
        .act_out(act_BL_to_TL),              // sends activation up
        .sum_out(sum_BL_to_BR)               // sends sum right
    );
    //(0,1)
    mac_unit mac_TR (
        .clk(clk), .rst(rst),
        .weight(weights[0][1]),
        .act_in(act_BR_to_TR),               // activation from below
        .sum_in(sum_TL_to_TR),               // sum in from left (0,0)
        .act_out(act_top_out_R),             // sends activation up
        .sum_out(sum_out_row_top)            // sends sum out of grid
    );
    //(1,1)
    mac_unit mac_BR (
        .clk(clk), .rst(rst),
        .weight(weights[1][1]),
        .act_in(act_in_cols[1]),             // activation vector
        .sum_in(sum_BL_to_BR),               // sum from left (1,0)
        .act_out(act_BR_to_TR),              // sends activation up
        .sum_out(sum_out_row_bot)            // Sends sum out of grid
    );
    
endmodule

systolic_array_V1/systolic_2x2TB.v
module systolic_2x2TB();

    reg clk, rst;
    reg [7:0] weights [0:1][0:1];
    reg [7:0] acts [0:1][0:1];
    reg [7:0] act_in_cols[0:1];
    wire [17:0] sum_out_row_bot, sum_out_row_top;

    systolic_2x2 dut (
        .clk(clk), .rst(rst), 
        .weights(weights), .act_in_cols(act_in_cols),
        .sum_out_row_bot(sum_out_row_bot), .sum_out_row_top(sum_out_row_top)
    );

    initial clk = 0;
    always #5 clk = ~clk;

    initial begin 
        $dumpfile("systolic_2x2.vcd");
        $dumpvars(0, systolic_2x2TB);

        // Clear values
        rst = 1; 
        weights[0][0] = 0; weights[0][1] = 0; // AUTOMATE LATER
        weights[1][0] = 0; weights[1][1] = 0;
        act_in_cols[0] = 0; act_in_cols[1] = 0;
        #10 rst = 0;

        //Set weights
        weights[0][0] = 8'd1; weights[0][1] = 8'd2;
        weights[1][0] = 8'd3; weights[1][1] = 8'd4;
        
        /* Transposed and delayed for feeding
            Cycle:    1    2    3
            Col 1:    -    7    8      <- row 1 of B: [7, 8], delayed 1 cycle
            Col 0:    5    6    -      <- row 0 of B: [5, 6]
        */

        //Set activation vector one row at a time
        
        // Cycle 1
        act_in_cols[1] = 8'd0;
        act_in_cols[0] = 8'd5;
            // wait a cycle for the stuff to calculate
            #10;
            // Check output
            $display("sum_out = [%d, %d] ([0,0])", sum_out_row_bot, sum_out_row_top);
        
        // Cycle 2
        act_in_cols[1] = 8'd7;
        act_in_cols[0] = 8'd6;
            #10;
            $display("sum_out = [%d, %d] ([43,0])", sum_out_row_bot, sum_out_row_top);

        // Cycle 3
        act_in_cols[1] = 8'd8;
        act_in_cols[0] = 8'd0;
            #10;
            $display("sum_out = [%d, %d] ([50,19])", sum_out_row_bot, sum_out_row_top);

        // Cycle 4 - DRAIN
            #10;
            $display("sum_out = [%d, %d] ([32,22])", sum_out_row_bot, sum_out_row_top);
        /*THE 32 COMES FROM the activation remaining in the MAC after use since
          there is no output for the activation value at the top ()*/ 
        #20;
        $finish;
    end
endmodule

systolic_array_V1/systolic_2x2.vcd
$date
	Thu May 14 19:32:33 2026
$end
$version
	Icarus Verilog
$end
$timescale
	1s
$end
$scope module systolic_2x2TB $end
$var wire 18 ! sum_out_row_top [17:0] $end
$var wire 18 " sum_out_row_bot [17:0] $end
$var reg 1 # clk $end
$var reg 1 $ rst $end
$scope module dut $end
$var wire 1 # clk $end
$var wire 1 $ rst $end
$var wire 18 % sum_out_row_top [17:0] $end
$var wire 18 & sum_out_row_bot [17:0] $end
$var wire 18 ' sum_TL_to_TR [17:0] $end
$var wire 18 ( sum_BL_to_BR [17:0] $end
$var wire 8 ) act_top_out_R [7:0] $end
$var wire 8 * act_top_out_L [7:0] $end
$var wire 8 + act_BR_to_TR [7:0] $end
$var wire 8 , act_BL_to_TL [7:0] $end
$var parameter 32 - N $end
$var parameter 66 . SUM_WIDTH $end
$var parameter 32 / WIDTH $end
$scope module mac_BL $end
$var wire 8 0 act_in [7:0] $end
$var wire 1 # clk $end
$var wire 1 $ rst $end
$var wire 18 1 sum_in [17:0] $end
$var wire 8 2 weight [7:0] $end
$var parameter 32 3 N $end
$var parameter 66 4 SUM_WIDTH $end
$var parameter 32 5 WIDTH $end
$var reg 8 6 act_out [7:0] $end
$var reg 18 7 sum_out [17:0] $end
$upscope $end
$scope module mac_BR $end
$var wire 8 8 act_in [7:0] $end
$var wire 1 # clk $end
$var wire 1 $ rst $end
$var wire 18 9 sum_in [17:0] $end
$var wire 8 : weight [7:0] $end
$var parameter 32 ; N $end
$var parameter 66 < SUM_WIDTH $end
$var parameter 32 = WIDTH $end
$var reg 8 > act_out [7:0] $end
$var reg 18 ? sum_out [17:0] $end
$upscope $end
$scope module mac_TL $end
$var wire 8 @ act_in [7:0] $end
$var wire 1 # clk $end
$var wire 1 $ rst $end
$var wire 18 A sum_in [17:0] $end
$var wire 8 B weight [7:0] $end
$var parameter 32 C N $end
$var parameter 66 D SUM_WIDTH $end
$var parameter 32 E WIDTH $end
$var reg 8 F act_out [7:0] $end
$var reg 18 G sum_out [17:0] $end
$upscope $end
$scope module mac_TR $end
$var wire 8 H act_in [7:0] $end
$var wire 1 # clk $end
$var wire 1 $ rst $end
$var wire 18 I sum_in [17:0] $end
$var wire 8 J weight [7:0] $end
$var parameter 32 K N $end
$var parameter 66 L SUM_WIDTH $end
$var parameter 32 M WIDTH $end
$var reg 8 N act_out [7:0] $end
$var reg 18 O sum_out [17:0] $end
$upscope $end
$upscope $end
$upscope $end
$enddefinitions $end
$comment Show the parameter values. $end
$dumpall
b1000 M
b10010 L
b10 K
b1000 E
b10010 D
b10 C
b1000 =
b10010 <
b10 ;
b1000 5
b10010 4
b10 3
b1000 /
b10010 .
b10 -
$end
#0
$dumpvars
bx O
bx N
b0 J
bx I
bx H
bx G
bx F
b0 B
b0 A
bx @
bx ?
bx >
b0 :
bx 9
b0 8
bx 7
bx 6
b0 2
b0 1
b0 0
bx ,
bx +
bx *
bx )
bx (
bx '
bx &
bx %
1$
0#
bx "
bx !
$end
#5
b0 '
b0 G
b0 I
b0 *
b0 F
b0 (
b0 7
b0 9
b0 ,
b0 6
b0 @
b0 !
b0 %
b0 O
b0 )
b0 N
b0 "
b0 &
b0 ?
b0 +
b0 >
b0 H
1#
#10
0#
b101 0
b100 :
b11 2
b10 J
b1 B
0$
#15
b1111 (
b1111 7
b1111 9
b101 ,
b101 6
b101 @
1#
#20
0#
b110 0
b111 8
#25
b101 '
b101 G
b101 I
b101 *
b101 F
b10010 (
b10010 7
b10010 9
b110 ,
b110 6
b110 @
b101011 "
b101011 &
b101011 ?
b111 +
b111 >
b111 H
1#
#30
0#
b0 0
b1000 8
#35
b110010 "
b110010 &
b110010 ?
b1000 +
b1000 >
b1000 H
b10011 !
b10011 %
b10011 O
b111 )
b111 N
b0 (
b0 7
b0 9
b0 ,
b0 6
b0 @
b110 '
b110 G
b110 I
b110 *
b110 F
1#
#40
0#
#45
b0 '
b0 G
b0 I
b0 *
b0 F
b10110 !
b10110 %
b10110 O
b1000 )
b1000 N
b100000 "
b100000 &
b100000 ?
1#
#50
0#
#55
b10000 !
b10000 %
b10000 O
1#
